odoo/addons/pos_invoice_required/README.rst
odoo/addons/pos_invoice_required/__init__.py
odoo/addons/pos_invoice_required/__manifest__.py
odoo/addons/pos_invoice_required/i18n/it.po
odoo/addons/pos_invoice_required/i18n/pos_invoice_required.pot
odoo/addons/pos_invoice_required/models/__init__.py
odoo/addons/pos_invoice_required/models/pos_config.py
odoo/addons/pos_invoice_required/models/pos_order.py
odoo/addons/pos_invoice_required/readme/CONFIGURE.rst
odoo/addons/pos_invoice_required/readme/CONTRIBUTORS.rst
odoo/addons/pos_invoice_required/readme/DESCRIPTION.rst
odoo/addons/pos_invoice_required/static/description/icon.png
odoo/addons/pos_invoice_required/static/description/index.html
odoo/addons/pos_invoice_required/static/src/js/models.js
odoo/addons/pos_invoice_required/static/src/js/screens.js
odoo/addons/pos_invoice_required/static/src/xml/templates.xml
odoo/addons/pos_invoice_required/views/pos_config_view.xml
odoo13_addon_pos_invoice_required-13.0.1.0.2.dev5.dist-info/METADATA
odoo13_addon_pos_invoice_required-13.0.1.0.2.dev5.dist-info/WHEEL
odoo13_addon_pos_invoice_required-13.0.1.0.2.dev5.dist-info/top_level.txt
odoo13_addon_pos_invoice_required-13.0.1.0.2.dev5.dist-info/RECORD
